my_demo/__init__.py
my_demo/main.py
my_demo-2019.3.31.dist-info/METADATA
my_demo-2019.3.31.dist-info/RECORD
my_demo-2019.3.31.dist-info/WHEEL
my_demo-2019.3.31.dist-info/top_level.txt
