Metadata-Version: 2.1
Name: my-demo
Version: 2019.3.31
Summary: A demo for python packaging.
Home-page: https://github.com/RongSong1993/zhiyundemo
Author: rongsong
Author-email: 18202888246@163.com
License: MIT
Keywords: demo
Platform: UNKNOWN
